{"sections":{"main":{"type":"article-template","settings":{"featured_image":"none","wide_display":true,"mobile_image_crop":"none","caption_content_background":"original","blog_breadcrumb":true,"blog_pagination":true,"blog_tags":false,"blog_byline":false,"read_time":true,"blog_date":true,"blog_author":false,"display_social_buttons":true,"blog_comment_count":true,"blog_additional_posts":false,"read_more_link":true,"toggle":false}},"article_images_columns_9YYPdk":{"type":"article-images-columns","blocks":{"text_block_rmPUyw":{"type":"text_block","settings":{"enable_image":true,"image":"shopify:\/\/shop_images\/rOSj_5DRTvC6_11d762f0-2278-4061-a2e9-32d766265795.jpg","image_url":"https:\/\/www.instagram.com\/p\/C2qUGTXJzgY\/"}}},"block_order":["text_block_rmPUyw"],"settings":{"css_class":"","custom_css":""}},"article_images_columns_6KNptC":{"type":"article-images-columns","blocks":{"text_block_Tfedbr":{"type":"text_block","settings":{"enable_image":true,"image":"shopify:\/\/shop_images\/h-C40IzlbcLA_a7180560-cf0c-4990-b77a-ac4ba692a597.jpg","image_url":"https:\/\/susanshaw.com\/products\/milly-flower-earrings"}},"text_block_Md3Rqe":{"type":"text_block","settings":{"enable_image":true,"image":"shopify:\/\/shop_images\/H3g-KTUWbppY_7cee920f-8e42-484d-92e4-7db8328efcb5.jpg","image_url":"https:\/\/susanshaw.com\/products\/becca-necklace"}}},"block_order":["text_block_Tfedbr","text_block_Md3Rqe"],"settings":{"css_class":"","custom_css":""}},"article_images_columns_cGwUqa":{"type":"article-images-columns","blocks":{"text_block_N6ANJf":{"type":"text_block","settings":{"enable_image":true,"image":"shopify:\/\/shop_images\/8cU3ID2dVl_o_bed2c72b-ace6-4617-ba46-73f053115cbd.jpg","image_url":"https:\/\/susanshaw.com\/products\/bentley-stone-bracelet"}},"text_block_pjXzyY":{"type":"text_block","settings":{"enable_image":true,"image":"shopify:\/\/shop_images\/QaK6sxm0lOUB_2783711c-84eb-45cd-954e-5dc4f27ee1b4.jpg","image_url":"https:\/\/susanshaw.com\/products\/sarabeth-pearl-drop-earrings"}}},"block_order":["text_block_N6ANJf","text_block_pjXzyY"],"settings":{"css_class":"","custom_css":""}}},"order":["main","article_images_columns_9YYPdk","article_images_columns_6KNptC","article_images_columns_cGwUqa"]}